openai_model_registry/data/__init__.py
openai_model_registry/data/checksums.txt
openai_model_registry/data/data-changelog.md
openai_model_registry/data/models.yaml
openai_model_registry/data/overrides.yaml
openai_model_registry/__init__.py
openai_model_registry/cli/__init__.py
openai_model_registry/cli/app.py
openai_model_registry/cli/commands/__init__.py
openai_model_registry/cli/commands/cache.py
openai_model_registry/cli/commands/data.py
openai_model_registry/cli/commands/models.py
openai_model_registry/cli/commands/providers.py
openai_model_registry/cli/commands/update.py
openai_model_registry/cli/formatters/__init__.py
openai_model_registry/cli/formatters/json.py
openai_model_registry/cli/formatters/table.py
openai_model_registry/cli/utils/__init__.py
openai_model_registry/cli/utils/helpers.py
openai_model_registry/cli/utils/options.py
openai_model_registry/config/__init__.py
openai_model_registry/config/data-changelog.md
openai_model_registry/config/parameter_constraints.yml
openai_model_registry/config_paths.py
openai_model_registry/config_result.py
openai_model_registry/constraints.py
openai_model_registry/data_manager.py
openai_model_registry/deprecation.py
openai_model_registry/errors.py
openai_model_registry/logging.py
openai_model_registry/model_version.py
openai_model_registry/pricing.py
openai_model_registry/py.typed
openai_model_registry/registry.py
openai_model_registry/schema_version.py
openai_model_registry/scripts/__init__.py
openai_model_registry/scripts/data_update.py
openai_model_registry/scripts/fetch_pricing_ostruct.py
openai_model_registry/scripts/update_registry.py
openai_model_registry-1.0.2.dist-info/LICENSE
openai_model_registry-1.0.2.dist-info/METADATA
openai_model_registry-1.0.2.dist-info/WHEEL
openai_model_registry-1.0.2.dist-info/entry_points.txt
openai_model_registry-1.0.2.dist-info/RECORD
