Metadata-Version: 2.3
Name: openai-model-registry
Version: 1.0.2
Summary: Registry for OpenAI models with capability and parameter validation
Author: Yaniv Golan
Author-email: yaniv@golan.name
Requires-Python: >=3.10,<4.0
Classifier: Programming Language :: Python :: 3
Classifier: Programming Language :: Python :: 3.10
Classifier: Programming Language :: Python :: 3.11
Classifier: Programming Language :: Python :: 3.12
Classifier: Programming Language :: Python :: 3.13
Requires-Dist: PyYAML (>=6.0.1,<7.0.0)
Requires-Dist: beautifulsoup4 (>=4.12.2,<5.0.0)
Requires-Dist: click (>=8.1.0,<8.2)
Requires-Dist: packaging (>=24.0,<25.0)
Requires-Dist: platformdirs (>=4.3.6,<5.0.0)
Requires-Dist: requests (>=2.31.0,<3.0.0)
Requires-Dist: rich (>=13.7.0)
Requires-Dist: rich-click (>=1.7.0)
Requires-Dist: semver (>=3.0.0,<4.0.0)
Requires-Dist: typing-extensions (>=4.9.0,<5.0.0)
